pkg/__init__.py
vuln_pub_sdk-0.0.2.dist-info/METADATA
vuln_pub_sdk-0.0.2.dist-info/WHEEL
vuln_pub_sdk-0.0.2.dist-info/top_level.txt
vuln_pub_sdk-0.0.2.dist-info/RECORD
