Metadata-Version: 2.1
Name: vuln-pub-sdk
Version: 0.0.2
Summary: Public SDK
Home-page: https://github.com/VulnCorp/vuln-pub-sdk
Author: VulnCorp
Author-email: admin@vulncorp.com
License: UNKNOWN
Project-URL: Bug Tracker, https://github.com/VulnCorp/vuln-pub-sdk/issues
Platform: UNKNOWN
Classifier: Programming Language :: Python :: 3
Classifier: License :: OSI Approved :: MIT License
Classifier: Operating System :: OS Independent
Requires-Python: >=3.6
